{
    "F_1": 205.0,
    "F_2": 191.83,
    "F_3": 183.64,
    "F_4": 183.23,
    "F_5": 191.35,
    "F_6": 195.61,
    "F_7": 186.84,
    "F_8": 202.59,
    "F_9": 196.79,
    "F_10": 181.27,
    "F_11": 181.69,
    "F_12": 184.25,
    "F_13": 204.04,
    "F_14": 194.08,
    "F_15": 204.04,
    "F_16": 186.44,
    "F_17": 188.94,
    "F_18": 204.32,
    "F_19": 182.64,
    "F_20": 180.17,
    "F_21": 190.83,
    "F_22": 183.76,
    "F_23": 193.52,
    "F_24": 197.27,
    "F_25": 205.94,
    "F_26": 184.69,
    "F_27": 180.0,
    "F_28": 192.02,
    "F_29": 194.49,
    "F_30": 185.52,
    "F_31": 195.49,
    "F_32": 184.88,
    "F_33": 192.17,
    "F_34": 185.47,
    "F_35": 195.68,
    "F_36": 178.85,
    "F_37": 188.4,
    "F_38": 184.12,
    "F_39": 196.04,
    "F_40": 197.87,
    "F_41": 177.87,
    "F_42": 188.46,
    "F_43": 182.29,
    "F_44": 190.16,
    "F_45": 189.56,
    "F_46": 198.79,
    "F_47": 188.03,
    "F_48": 199.21,
    "F_49": 189.86,
    "F_50": 202.69,
    "F_51": 186.92,
    "F_52": 193.61,
    "F_53": 186.68,
    "F_54": 186.13,
    "F_55": 186.5,
    "F_56": 186.29,
    "F_57": 193.36,
    "F_58": 184.18,
    "F_59": 191.59,
    "F_60": 188.93,
    "F_61": 187.65,
    "F_62": 184.57,
    "F_63": 188.83,
    "F_64": 199.96,
    "F_65": 205.63,
    "F_66": 200.74,
    "F_67": 203.32,
    "F_68": 190.84,
    "F_69": 195.51,
    "F_70": 191.42,
    "F_71": 198.03,
    "F_72": 171.02,
    "F_73": 200.77,
    "F_74": 189.73,
    "F_75": 187.73,
    "F_76": 194.36,
    "F_77": 201.45,
    "F_78": 184.41,
    "F_79": 173.5,
    "F_80": 182.04,
    "F_81": 180.73,
    "F_82": 166.95,
    "F_83": 197.16,
    "F_84": 197.56,
    "F_85": 202.97,
    "F_86": 194.13,
    "F_87": 194.6,
    "F_88": 203.82,
    "F_89": 185.95,
    "F_90": 201.01,
    "F_91": 194.95,
    "F_92": 189.52,
    "F_93": 171.4,
    "F_94": 188.44,
    "F_95": 211.85,
    "F_96": 171.62,
    "F_97": 198.09,
    "F_98": 193.14,
    "F_99": 183.99,
    "F_100": 184.44
}