{
    "F_1": 135.93,
    "F_2": 133.15,
    "F_3": 118.3,
    "F_4": 109.36,
    "F_5": 123.86,
    "F_6": 133.48,
    "F_7": 126.42,
    "F_8": 134.45,
    "F_9": 122.61,
    "F_10": 112.94,
    "F_11": 124.41,
    "F_12": 117.25,
    "F_13": 133.1,
    "F_14": 119.21,
    "F_15": 131.81,
    "F_16": 118.52,
    "F_17": 128.91,
    "F_18": 121.65,
    "F_19": 117.3,
    "F_20": 110.87,
    "F_21": 138.51,
    "F_22": 118.71,
    "F_23": 129.27,
    "F_24": 131.25,
    "F_25": 141.95,
    "F_26": 116.87,
    "F_27": 126.74,
    "F_28": 125.54,
    "F_29": 136.61,
    "F_30": 114.97,
    "F_31": 127.61,
    "F_32": 131.74,
    "F_33": 124.75,
    "F_34": 115.98,
    "F_35": 132.07,
    "F_36": 113.84,
    "F_37": 121.58,
    "F_38": 134.17,
    "F_39": 124.81,
    "F_40": 149.68,
    "F_41": 117.68,
    "F_42": 132.25,
    "F_43": 110.74,
    "F_44": 125.59,
    "F_45": 123.27,
    "F_46": 125.2,
    "F_47": 124.28,
    "F_48": 125.56,
    "F_49": 122.85,
    "F_50": 119.39,
    "F_51": 110.11,
    "F_52": 133.0,
    "F_53": 128.81,
    "F_54": 110.07,
    "F_55": 125.42,
    "F_56": 114.57,
    "F_57": 121.9,
    "F_58": 107.98,
    "F_59": 118.89,
    "F_60": 124.87,
    "F_61": 101.74,
    "F_62": 114.37,
    "F_63": 137.03,
    "F_64": 123.55,
    "F_65": 132.66,
    "F_66": 132.25,
    "F_67": 135.42,
    "F_68": 113.45,
    "F_69": 133.3,
    "F_70": 107.24,
    "F_71": 126.13,
    "F_72": 116.76,
    "F_73": 135.15,
    "F_74": 112.35,
    "F_75": 120.03,
    "F_76": 117.79,
    "F_77": 129.61,
    "F_78": 122.27,
    "F_79": 108.53,
    "F_80": 111.48,
    "F_81": 125.21,
    "F_82": 114.15,
    "F_83": 119.88,
    "F_84": 126.93,
    "F_85": 135.68,
    "F_86": 136.66,
    "F_87": 129.83,
    "F_88": 129.88,
    "F_89": 127.87,
    "F_90": 131.32,
    "F_91": 136.1,
    "F_92": 124.75,
    "F_93": 98.77,
    "F_94": 109.18,
    "F_95": 158.88,
    "F_96": 115.43,
    "F_97": 120.25,
    "F_98": 118.79,
    "F_99": 113.63,
    "F_100": 127.33
}