{
    "F_1": 166.3,
    "F_2": 158.02,
    "F_3": 164.84,
    "F_4": 154.48,
    "F_5": 162.42,
    "F_6": 156.27,
    "F_7": 163.03,
    "F_8": 153.3,
    "F_9": 144.3,
    "F_10": 156.27,
    "F_11": 149.3,
    "F_12": 170.07,
    "F_13": 179.46,
    "F_14": 181.03,
    "F_15": 160.83,
    "F_16": 161.53,
    "F_17": 157.1,
    "F_18": 162.5,
    "F_19": 172.63,
    "F_20": 171.28,
    "F_21": 166.25,
    "F_22": 171.4,
    "F_23": 153.33,
    "F_24": 148.58,
    "F_25": 165.27,
    "F_26": 165.6,
    "F_27": 160.89,
    "F_28": 167.76,
    "F_29": 161.51,
    "F_30": 180.53,
    "F_31": 160.84,
    "F_32": 161.28,
    "F_33": 167.55,
    "F_34": 179.89,
    "F_35": 171.13,
    "F_36": 159.41,
    "F_37": 153.21,
    "F_38": 162.42,
    "F_39": 174.63,
    "F_40": 162.09,
    "F_41": 164.68,
    "F_42": 160.3,
    "F_43": 169.82,
    "F_44": 172.1,
    "F_45": 163.76,
    "F_46": 182.09,
    "F_47": 164.93,
    "F_48": 177.34,
    "F_49": 158.41,
    "F_50": 176.83,
    "F_51": 181.95,
    "F_52": 179.0,
    "F_53": 162.35,
    "F_54": 178.81,
    "F_55": 167.35,
    "F_56": 172.87,
    "F_57": 181.59,
    "F_58": 161.8,
    "F_59": 183.65,
    "F_60": 156.69,
    "F_61": 169.54,
    "F_62": 160.17,
    "F_63": 165.89,
    "F_64": 170.51,
    "F_65": 169.66,
    "F_66": 169.96,
    "F_67": 171.7,
    "F_68": 180.32,
    "F_69": 158.42,
    "F_70": 175.83,
    "F_71": 171.73,
    "F_72": 178.42,
    "F_73": 174.45,
    "F_74": 165.13,
    "F_75": 164.78,
    "F_76": 159.49,
    "F_77": 170.26,
    "F_78": 157.95,
    "F_79": 171.86,
    "F_80": 183.97,
    "F_81": 153.07,
    "F_82": 163.45,
    "F_83": 168.39,
    "F_84": 185.16,
    "F_85": 182.17,
    "F_86": 165.8,
    "F_87": 158.96,
    "F_88": 182.53,
    "F_89": 174.35,
    "F_90": 168.35,
    "F_91": 155.54,
    "F_92": 154.86,
    "F_93": 173.59,
    "F_94": 161.27,
    "F_95": 145.4,
    "F_96": 162.99,
    "F_97": 191.16,
    "F_98": 191.45,
    "F_99": 173.74,
    "F_100": 167.18
}